.gitignore
.travis.yml
.venv
LICENSE
MANIFEST.in
README.md
local-requirements.txt
new_version.py
requirements.txt
setup.py
tox.ini
sanetime/__init__.py
sanetime/constants.py
sanetime/dj.py
sanetime/error.py
sanetime/sanedelta.py
sanetime/sanespan.py
sanetime/sanetime.py
sanetime/sanetztime.py
sanetime/test/.gitignore
sanetime/test/__init__.py
sanetime/test/test_delta.py
sanetime/test/test_time.py
sanetime/test/test_tztime.py
sanetime_py3.egg-info/PKG-INFO
sanetime_py3.egg-info/SOURCES.txt
sanetime_py3.egg-info/dependency_links.txt
sanetime_py3.egg-info/requires.txt
sanetime_py3.egg-info/top_level.txt